xstr/__init__.py
xstr/dstr.py
xstr/hstr.py
xstr/ustr.py
xstr/xstr.py
xstr-0.0.2.dist-info/LICENSE
xstr-0.0.2.dist-info/METADATA
xstr-0.0.2.dist-info/WHEEL
xstr-0.0.2.dist-info/top_level.txt
xstr-0.0.2.dist-info/RECORD
