Metadata-Version: 2.1
Name: xstr
Version: 0.0.2
Summary: package for converting strings to common ones, contains ustr UnderlineString dstr DotString hstr HyphenString
Author-email: Donald Guiles <donaldg.dev@gmail.com>
Project-URL: Homepage, https://github.com/Donny-GUI/xstr
Project-URL: Bug Tracker, https://github.com/Donny-GUI/xstr/issues
Classifier: Programming Language :: Python :: 3
Classifier: License :: OSI Approved :: MIT License
Classifier: Operating System :: OS Independent
Requires-Python: >=3.7
License-File: LICENSE
